{"assignment_list": [
[
{"value": "1f1aa648"},
{"value": "d7c1f5"},
{"value": "1fff"},
{"value": "3c2ff4"},
{"value": "9"},
{"value": "4c6e18e"},
{"value": "aa"},
{"value": "698d"},
{"value": "25c"},
{"value": "477657b4"},
{"value": "5c409ca5"},
{"value": "1fa4b5"},
{"value": "73f"},
{"value": "0"},
{"value": "a8"},
{"value": "3a42c"},
{"value": "0"},
{"value": "159b4fa8"},
{"value": "2c9f8"},
{"value": "1836b03a"},
{"value": "0"},
{"value": "1d9c9"},
{"value": "3ed"},
{"value": "8"},
{"value": "2d"},
{"value": "16d36a5d"},
{"value": "0"},
{"value": "4f"},
{"value": "0"},
{"value": "2f"}
],
[
{"value": "4385ef9"},
{"value": "7b9d592"},
{"value": "1fff"},
{"value": "e96b2c"},
{"value": "8"},
{"value": "6c9026e"},
{"value": "15b"},
{"value": "1bf5b"},
{"value": "737"},
{"value": "6721e9cc"},
{"value": "d42b9c51"},
{"value": "c63f9"},
{"value": "3c39"},
{"value": "0"},
{"value": "b7"},
{"value": "1c0cc"},
{"value": "60"},
{"value": "1f26198a"},
{"value": "104c1"},
{"value": "16705165"},
{"value": "0"},
{"value": "23dad"},
{"value": "4a4"},
{"value": "4"},
{"value": "10"},
{"value": "2f897e2"},
{"value": "0"},
{"value": "25"},
{"value": "0"},
{"value": "15"}
],
[
{"value": "552ae4b"},
{"value": "268844b"},
{"value": "1fff"},
{"value": "c404b"},
{"value": "e"},
{"value": "415663a"},
{"value": "28a"},
{"value": "12290"},
{"value": "dc7"},
{"value": "c18d7eac"},
{"value": "eaa59de9"},
{"value": "daa84"},
{"value": "d90"},
{"value": "0"},
{"value": "48"},
{"value": "122a5"},
{"value": "0"},
{"value": "41170dd"},
{"value": "1b708"},
{"value": "3ab6903"},
{"value": "0"},
{"value": "1796"},
{"value": "38c"},
{"value": "a"},
{"value": "4b"},
{"value": "22c6b289"},
{"value": "0"},
{"value": "1"},
{"value": "0"},
{"value": "34"}
],
[
{"value": "1a5ccb55"},
{"value": "6e541e7"},
{"value": "1fff"},
{"value": "df708"},
{"value": "a"},
{"value": "efa134"},
{"value": "2a5"},
{"value": "18d4b"},
{"value": "c53"},
{"value": "93752b10"},
{"value": "338ef4b0"},
{"value": "39c1f"},
{"value": "3f4e"},
{"value": "0"},
{"value": "ba"},
{"value": "165d7"},
{"value": "80"},
{"value": "4b943c2"},
{"value": "13ca"},
{"value": "1c51010b"},
{"value": "0"},
{"value": "1c52b"},
{"value": "5cc"},
{"value": "8"},
{"value": "23"},
{"value": "24043ce0"},
{"value": "0"},
{"value": "77"},
{"value": "0"},
{"value": "6a"}
],
[
{"value": "3d84838"},
{"value": "5133ed5"},
{"value": "1fff"},
{"value": "8651c2"},
{"value": "6"},
{"value": "75c98eb"},
{"value": "190"},
{"value": "1e631"},
{"value": "122"},
{"value": "d17183e2"},
{"value": "ce6f16be"},
{"value": "1c6f30"},
{"value": "2723"},
{"value": "0"},
{"value": "74"},
{"value": "20af9"},
{"value": "80"},
{"value": "19cceee5"},
{"value": "3af7d"},
{"value": "245603"},
{"value": "0"},
{"value": "332d7"},
{"value": "598"},
{"value": "b"},
{"value": "58"},
{"value": "1d80160f"},
{"value": "0"},
{"value": "2f"},
{"value": "0"},
{"value": "5c"}
],
[
{"value": "18766f19"},
{"value": "78c6669"},
{"value": "1fff"},
{"value": "54e500"},
{"value": "d"},
{"value": "320dbf9"},
{"value": "28a"},
{"value": "54d4"},
{"value": "6c9"},
{"value": "da9b9541"},
{"value": "bdc6c68a"},
{"value": "1d2de"},
{"value": "4df"},
{"value": "0"},
{"value": "2c"},
{"value": "2326e"},
{"value": "0"},
{"value": "3a217f4"},
{"value": "1a7e6"},
{"value": "c918819"},
{"value": "0"},
{"value": "27412"},
{"value": "6ef"},
{"value": "e"},
{"value": "42"},
{"value": "5184e5f"},
{"value": "0"},
{"value": "46"},
{"value": "0"},
{"value": "38"}
],
[
{"value": "1293fccc"},
{"value": "551e7e"},
{"value": "1fff"},
{"value": "b09838"},
{"value": "4"},
{"value": "56c5328"},
{"value": "64"},
{"value": "546b"},
{"value": "a0"},
{"value": "fcde11d6"},
{"value": "59af8eff"},
{"value": "7d146"},
{"value": "1f4c"},
{"value": "0"},
{"value": "27"},
{"value": "10821"},
{"value": "40"},
{"value": "196133e8"},
{"value": "311a4"},
{"value": "1c2194cc"},
{"value": "0"},
{"value": "2801c"},
{"value": "675"},
{"value": "e"},
{"value": "38"},
{"value": "20645ad6"},
{"value": "0"},
{"value": "45"},
{"value": "0"},
{"value": "28"}
],
[
{"value": "658a275"},
{"value": "674df4b"},
{"value": "1fff"},
{"value": "95d823"},
{"value": "b"},
{"value": "2c8f9f9"},
{"value": "229"},
{"value": "10b27"},
{"value": "d52"},
{"value": "c65efcbc"},
{"value": "9b9ba68b"},
{"value": "afae2"},
{"value": "3243"},
{"value": "0"},
{"value": "2f"},
{"value": "1fd10"},
{"value": "0"},
{"value": "4a5b522"},
{"value": "3dadd"},
{"value": "86588c2"},
{"value": "0"},
{"value": "3ef53"},
{"value": "10b"},
{"value": "c"},
{"value": "2c"},
{"value": "348ab183"},
{"value": "0"},
{"value": "22"},
{"value": "0"},
{"value": "10"}
],
[
{"value": "16db24e1"},
{"value": "1bf8c22"},
{"value": "1fff"},
{"value": "7c6a52"},
{"value": "8"},
{"value": "58931f2"},
{"value": "ba"},
{"value": "18e7a"},
{"value": "7ea"},
{"value": "5b60a4c1"},
{"value": "9c7bef04"},
{"value": "1b38cc"},
{"value": "3d5a"},
{"value": "0"},
{"value": "46"},
{"value": "225a4"},
{"value": "80"},
{"value": "90498ec"},
{"value": "37f97"},
{"value": "f3904d0"},
{"value": "0"},
{"value": "20c0e"},
{"value": "1c0"},
{"value": "5"},
{"value": "2c"},
{"value": "c532172"},
{"value": "0"},
{"value": "41"},
{"value": "0"},
{"value": "35"}
],
[
{"value": "f0081bf"},
{"value": "9f3802"},
{"value": "1fff"},
{"value": "8d1d9e"},
{"value": "8"},
{"value": "599c366"},
{"value": "127"},
{"value": "4e06"},
{"value": "330"},
{"value": "7f90d8f6"},
{"value": "78d38d42"},
{"value": "e950d"},
{"value": "1db1"},
{"value": "0"},
{"value": "cd"},
{"value": "efd4"},
{"value": "60"},
{"value": "1eaa3166"},
{"value": "17c3b"},
{"value": "28a3e86"},
{"value": "0"},
{"value": "1eba0"},
{"value": "1f0"},
{"value": "e"},
{"value": "70"},
{"value": "187008ed"},
{"value": "0"},
{"value": "4a"},
{"value": "0"},
{"value": "15"}
],
[
{"value": "93abda4"},
{"value": "4b8505c"},
{"value": "1fff"},
{"value": "267f14"},
{"value": "e"},
{"value": "43a5e8f"},
{"value": "2d7"},
{"value": "18612"},
{"value": "26c"},
{"value": "27abe284"},
{"value": "3c97338e"},
{"value": "16d290"},
{"value": "2b11"},
{"value": "0"},
{"value": "dd"},
{"value": "296c4"},
{"value": "0"},
{"value": "9333909"},
{"value": "2582b"},
{"value": "1b23828a"},
{"value": "0"},
{"value": "329ba"},
{"value": "2c8"},
{"value": "7"},
{"value": "5e"},
{"value": "7605d29"},
{"value": "0"},
{"value": "7d"},
{"value": "0"},
{"value": "3c"}
],
[
{"value": "1a784f3c"},
{"value": "38f4eb5"},
{"value": "1fff"},
{"value": "7ef94b"},
{"value": "c"},
{"value": "47b4e62"},
{"value": "249"},
{"value": "7d64"},
{"value": "8b"},
{"value": "36497d13"},
{"value": "16273eff"},
{"value": "58cf0"},
{"value": "cce"},
{"value": "0"},
{"value": "ac"},
{"value": "13167"},
{"value": "c0"},
{"value": "10471c26"},
{"value": "3c26"},
{"value": "1d35a98f"},
{"value": "0"},
{"value": "3ff79"},
{"value": "5dc"},
{"value": "d"},
{"value": "70"},
{"value": "34e9cef8"},
{"value": "0"},
{"value": "7a"},
{"value": "0"},
{"value": "4f"}
],
[
{"value": "1c305fe1"},
{"value": "6ae479f"},
{"value": "1fff"},
{"value": "b991c5"},
{"value": "a"},
{"value": "58deac1"},
{"value": "249"},
{"value": "1efc8"},
{"value": "db1"},
{"value": "60bce15"},
{"value": "725ad52b"},
{"value": "516c4"},
{"value": "514"},
{"value": "0"},
{"value": "d3"},
{"value": "3c1f0"},
{"value": "0"},
{"value": "7cf665"},
{"value": "3db49"},
{"value": "104a12eb"},
{"value": "0"},
{"value": "606f"},
{"value": "611"},
{"value": "6"},
{"value": "3d"},
{"value": "1e9d1c82"},
{"value": "0"},
{"value": "12"},
{"value": "0"},
{"value": "21"}
],
[
{"value": "8f2218c"},
{"value": "35a3547"},
{"value": "1fff"},
{"value": "de414f"},
{"value": "3"},
{"value": "7492a7d"},
{"value": "60"},
{"value": "118a0"},
{"value": "8"},
{"value": "ecc2c261"},
{"value": "638c893f"},
{"value": "d61fd"},
{"value": "16fe"},
{"value": "0"},
{"value": "de"},
{"value": "171f0"},
{"value": "0"},
{"value": "149a1eea"},
{"value": "2d4ba"},
{"value": "ca91138"},
{"value": "0"},
{"value": "1850a"},
{"value": "34a"},
{"value": "3"},
{"value": "72"},
{"value": "1e4a18da"},
{"value": "0"},
{"value": "38"},
{"value": "0"},
{"value": "1d"}
],
[
{"value": "16f1d99e"},
{"value": "1598ebd"},
{"value": "1fff"},
{"value": "810831"},
{"value": "7"},
{"value": "6c9287c"},
{"value": "8d"},
{"value": "1469"},
{"value": "3d0"},
{"value": "e1550c93"},
{"value": "cd417eab"},
{"value": "7a22f"},
{"value": "31af"},
{"value": "0"},
{"value": "5f"},
{"value": "3a442"},
{"value": "0"},
{"value": "4f12851"},
{"value": "1f84b"},
{"value": "178b62e9"},
{"value": "0"},
{"value": "22f67"},
{"value": "4ee"},
{"value": "6"},
{"value": "30"},
{"value": "26009211"},
{"value": "0"},
{"value": "32"},
{"value": "0"},
{"value": "19"}
],
[
{"value": "181f7770"},
{"value": "7d513a3"},
{"value": "1fff"},
{"value": "62f730"},
{"value": "8"},
{"value": "72e3df4"},
{"value": "233"},
{"value": "5cdf"},
{"value": "b69"},
{"value": "16a4428b"},
{"value": "8c96fad"},
{"value": "19c6a1"},
{"value": "12f1"},
{"value": "0"},
{"value": "64"},
{"value": "1a5ac"},
{"value": "40"},
{"value": "f6d1477"},
{"value": "24f3b"},
{"value": "8ffbe6e"},
{"value": "0"},
{"value": "3551d"},
{"value": "246"},
{"value": "9"},
{"value": "5d"},
{"value": "3cda457"},
{"value": "0"},
{"value": "47"},
{"value": "0"},
{"value": "26"}
],
[
{"value": "53e82ce"},
{"value": "5aa71d2"},
{"value": "1fff"},
{"value": "b99ee1"},
{"value": "b"},
{"value": "4b8a5e2"},
{"value": "1f8"},
{"value": "1ce5d"},
{"value": "66e"},
{"value": "93b303d1"},
{"value": "b2f35cfd"},
{"value": "fd8e9"},
{"value": "3003"},
{"value": "0"},
{"value": "5e"},
{"value": "2ff31"},
{"value": "0"},
{"value": "12be8601"},
{"value": "c728"},
{"value": "73a433d"},
{"value": "0"},
{"value": "3b4e6"},
{"value": "33f"},
{"value": "f"},
{"value": "51"},
{"value": "2b767be8"},
{"value": "0"},
{"value": "5c"},
{"value": "0"},
{"value": "1c"}
],
[
{"value": "16f0a2ff"},
{"value": "4cb0d3a"},
{"value": "1fff"},
{"value": "e4d610"},
{"value": "9"},
{"value": "42548bd"},
{"value": "32b"},
{"value": "11cd1"},
{"value": "880"},
{"value": "20cbb55a"},
{"value": "d53a81f9"},
{"value": "93989"},
{"value": "f10"},
{"value": "0"},
{"value": "89"},
{"value": "230fa"},
{"value": "0"},
{"value": "6dedd01"},
{"value": "36301"},
{"value": "ffdd214"},
{"value": "0"},
{"value": "11002"},
{"value": "4e8"},
{"value": "f"},
{"value": "7e"},
{"value": "c7e5535"},
{"value": "0"},
{"value": "2f"},
{"value": "0"},
{"value": "59"}
],
[
{"value": "213cc67"},
{"value": "59fcac1"},
{"value": "1fff"},
{"value": "b5c2cc"},
{"value": "2"},
{"value": "5c342a5"},
{"value": "1ef"},
{"value": "16e18"},
{"value": "956"},
{"value": "6d61082f"},
{"value": "f557bfc9"},
{"value": "145c1d"},
{"value": "2458"},
{"value": "0"},
{"value": "ae"},
{"value": "1af34"},
{"value": "80"},
{"value": "129c567b"},
{"value": "1eac7"},
{"value": "1fcc466b"},
{"value": "0"},
{"value": "19107"},
{"value": "2f0"},
{"value": "1"},
{"value": "34"},
{"value": "10cc6297"},
{"value": "0"},
{"value": "3"},
{"value": "0"},
{"value": "8"}
],
[
{"value": "d3ea4d5"},
{"value": "147100a"},
{"value": "1fff"},
{"value": "7cc0f8"},
{"value": "a"},
{"value": "3b9c205"},
{"value": "120"},
{"value": "15051"},
{"value": "2ea"},
{"value": "3c574e95"},
{"value": "15c4ebff"},
{"value": "108549"},
{"value": "480"},
{"value": "0"},
{"value": "3b"},
{"value": "2c493"},
{"value": "0"},
{"value": "1fc9a399"},
{"value": "23aab"},
{"value": "444ad0a"},
{"value": "0"},
{"value": "eb61"},
{"value": "4c1"},
{"value": "f"},
{"value": "5c"},
{"value": "f7647ac"},
{"value": "0"},
{"value": "10"},
{"value": "0"},
{"value": "60"}
],
[
{"value": "17def14d"},
{"value": "7f9407b"},
{"value": "1fff"},
{"value": "4226c9"},
{"value": "7"},
{"value": "37857ca"},
{"value": "2e9"},
{"value": "10c1b"},
{"value": "25"},
{"value": "bf2731a5"},
{"value": "6adbea93"},
{"value": "8e02d"},
{"value": "2fb3"},
{"value": "0"},
{"value": "ec"},
{"value": "32bf8"},
{"value": "0"},
{"value": "1ea59c58"},
{"value": "fd62"},
{"value": "1bdb79b6"},
{"value": "0"},
{"value": "21680"},
{"value": "103"},
{"value": "a"},
{"value": "2e"},
{"value": "2d26b305"},
{"value": "0"},
{"value": "76"},
{"value": "0"},
{"value": "11"}
],
[
{"value": "134ef3c7"},
{"value": "7e5e1a"},
{"value": "1fff"},
{"value": "124141"},
{"value": "d"},
{"value": "5b8af8a"},
{"value": "383"},
{"value": "9bb1"},
{"value": "bbf"},
{"value": "2f1021a5"},
{"value": "b2865654"},
{"value": "16c8df"},
{"value": "3710"},
{"value": "0"},
{"value": "cd"},
{"value": "220fd"},
{"value": "0"},
{"value": "ebecdaf"},
{"value": "1ef1e"},
{"value": "1764fe13"},
{"value": "0"},
{"value": "3f517"},
{"value": "a2"},
{"value": "9"},
{"value": "46"},
{"value": "2cb081be"},
{"value": "0"},
{"value": "33"},
{"value": "0"},
{"value": "9"}
],
[
{"value": "180a8818"},
{"value": "37a5cbb"},
{"value": "1fff"},
{"value": "1a365"},
{"value": "4"},
{"value": "708d45b"},
{"value": "52"},
{"value": "141cb"},
{"value": "157"},
{"value": "843e7916"},
{"value": "2c08f5e3"},
{"value": "11feb4"},
{"value": "1d12"},
{"value": "0"},
{"value": "66"},
{"value": "37e96"},
{"value": "40"},
{"value": "1d9ec065"},
{"value": "4cfd"},
{"value": "1e5345de"},
{"value": "0"},
{"value": "d288"},
{"value": "6d9"},
{"value": "c"},
{"value": "7b"},
{"value": "44f0ed6"},
{"value": "0"},
{"value": "49"},
{"value": "0"},
{"value": "4d"}
],
[
{"value": "11163173"},
{"value": "7ffffff"},
{"value": "1fff"},
{"value": "39e4f3"},
{"value": "6"},
{"value": "316fa28"},
{"value": "260"},
{"value": "15cc3"},
{"value": "497"},
{"value": "619b3af1"},
{"value": "d13bb80a"},
{"value": "d6e42"},
{"value": "3e1"},
{"value": "0"},
{"value": "80"},
{"value": "8939"},
{"value": "80"},
{"value": "1bc9ea17"},
{"value": "3ad37"},
{"value": "18a0a346"},
{"value": "0"},
{"value": "14f4e"},
{"value": "11e"},
{"value": "0"},
{"value": "22"},
{"value": "91c01cc"},
{"value": "0"},
{"value": "18"},
{"value": "0"},
{"value": "e"}
],
[
{"value": "1b74aea7"},
{"value": "7ffffff"},
{"value": "1fff"},
{"value": "ab5977"},
{"value": "9"},
{"value": "3a7b2ff"},
{"value": "395"},
{"value": "8bd5"},
{"value": "9f6"},
{"value": "7fde8e21"},
{"value": "fcf25a12"},
{"value": "379f6"},
{"value": "2942"},
{"value": "0"},
{"value": "25"},
{"value": "e785"},
{"value": "0"},
{"value": "18f7e2a6"},
{"value": "14d3b"},
{"value": "cf9d80e"},
{"value": "0"},
{"value": "1a5d6"},
{"value": "2dc"},
{"value": "0"},
{"value": "7e"},
{"value": "3b217a9"},
{"value": "0"},
{"value": "5d"},
{"value": "0"},
{"value": "69"}
],
[
{"value": "18337647"},
{"value": "7ffffff"},
{"value": "1fff"},
{"value": "b7de01"},
{"value": "e"},
{"value": "3b92887"},
{"value": "3f8"},
{"value": "19e46"},
{"value": "ccd"},
{"value": "8f14266c"},
{"value": "6705ce8d"},
{"value": "72e39"},
{"value": "295d"},
{"value": "0"},
{"value": "c5"},
{"value": "3a031"},
{"value": "80"},
{"value": "ea892ee"},
{"value": "6a0"},
{"value": "9d5f0bc"},
{"value": "0"},
{"value": "39151"},
{"value": "6a3"},
{"value": "0"},
{"value": "28"},
{"value": "1565b585"},
{"value": "0"},
{"value": "46"},
{"value": "0"},
{"value": "48"}
],
[
{"value": "e8de3d6"},
{"value": "7f193ed"},
{"value": "1fff"},
{"value": "7d85cc"},
{"value": "7"},
{"value": "1ba24da"},
{"value": "1c6"},
{"value": "277d"},
{"value": "d24"},
{"value": "1071103"},
{"value": "efc414b5"},
{"value": "16db81"},
{"value": "1422"},
{"value": "0"},
{"value": "3a"},
{"value": "26aa1"},
{"value": "0"},
{"value": "178d38a6"},
{"value": "6b5c"},
{"value": "1ec95d09"},
{"value": "0"},
{"value": "16972"},
{"value": "71a"},
{"value": "3"},
{"value": "7f"},
{"value": "306994ee"},
{"value": "0"},
{"value": "49"},
{"value": "0"},
{"value": "52"}
],
[
{"value": "11b9d964"},
{"value": "c5160e"},
{"value": "1fff"},
{"value": "25bf50"},
{"value": "7"},
{"value": "9bccf8"},
{"value": "e3"},
{"value": "12d55"},
{"value": "850"},
{"value": "f42f2b5d"},
{"value": "ff3edc9c"},
{"value": "da1d8"},
{"value": "25ea"},
{"value": "0"},
{"value": "64"},
{"value": "2d072"},
{"value": "0"},
{"value": "e56c2f2"},
{"value": "343f4"},
{"value": "63f10fa"},
{"value": "0"},
{"value": "71d7"},
{"value": "2e4"},
{"value": "7"},
{"value": "65"},
{"value": "357a132c"},
{"value": "0"},
{"value": "30"},
{"value": "0"},
{"value": "4b"}
],
[
{"value": "12723ed5"},
{"value": "5f64314"},
{"value": "1fff"},
{"value": "bf98d4"},
{"value": "6"},
{"value": "4d4d1e9"},
{"value": "f1"},
{"value": "115e3"},
{"value": "5d3"},
{"value": "3a4b132e"},
{"value": "5b8c05e2"},
{"value": "b1e13"},
{"value": "3f0d"},
{"value": "0"},
{"value": "f5"},
{"value": "2a46d"},
{"value": "80"},
{"value": "1b846973"},
{"value": "3c928"},
{"value": "f068ecb"},
{"value": "0"},
{"value": "15255"},
{"value": "37e"},
{"value": "2"},
{"value": "72"},
{"value": "e80a795"},
{"value": "0"},
{"value": "49"},
{"value": "0"},
{"value": "68"}
],
[
{"value": "11a49c4"},
{"value": "4a7413f"},
{"value": "1fff"},
{"value": "423936"},
{"value": "4"},
{"value": "799ff3e"},
{"value": "286"},
{"value": "6c9c"},
{"value": "3e6"},
{"value": "90c07539"},
{"value": "e581ecd9"},
{"value": "16978"},
{"value": "cc6"},
{"value": "0"},
{"value": "9f"},
{"value": "99c1"},
{"value": "80"},
{"value": "f878caf"},
{"value": "c292"},
{"value": "bcf338f"},
{"value": "0"},
{"value": "23978"},
{"value": "391"},
{"value": "e"},
{"value": "d"},
{"value": "d212e39"},
{"value": "0"},
{"value": "1f"},
{"value": "0"},
{"value": "48"}
],
[
{"value": "e9b4e80"},
{"value": "6ec6dfe"},
{"value": "1fff"},
{"value": "96b2bc"},
{"value": "2"},
{"value": "5c64c2b"},
{"value": "245"},
{"value": "a9bf"},
{"value": "e5b"},
{"value": "1bcef02d"},
{"value": "c1fd8f51"},
{"value": "68155"},
{"value": "30c"},
{"value": "0"},
{"value": "8d"},
{"value": "1122e"},
{"value": "80"},
{"value": "84dc4eb"},
{"value": "38bf2"},
{"value": "f7ebdc0"},
{"value": "0"},
{"value": "3f7b"},
{"value": "3d4"},
{"value": "8"},
{"value": "b"},
{"value": "33ac79a1"},
{"value": "0"},
{"value": "64"},
{"value": "0"},
{"value": "61"}
],
[
{"value": "8ee6025"},
{"value": "11279a"},
{"value": "1fff"},
{"value": "14e993"},
{"value": "8"},
{"value": "1a63e86"},
{"value": "34b"},
{"value": "1f640"},
{"value": "4cd"},
{"value": "f19ccfa6"},
{"value": "5dcc00bf"},
{"value": "29a5c"},
{"value": "25fd"},
{"value": "0"},
{"value": "b"},
{"value": "32c64"},
{"value": "c0"},
{"value": "e1da497"},
{"value": "3cfb4"},
{"value": "1b3438a2"},
{"value": "0"},
{"value": "36a82"},
{"value": "18a"},
{"value": "2"},
{"value": "47"},
{"value": "3abaa53c"},
{"value": "0"},
{"value": "49"},
{"value": "0"},
{"value": "d"}
],
[
{"value": "586dc6f"},
{"value": "4b42cf5"},
{"value": "1fff"},
{"value": "303c33"},
{"value": "8"},
{"value": "6a42b88"},
{"value": "1f5"},
{"value": "1c58a"},
{"value": "a43"},
{"value": "7ff70a12"},
{"value": "999673b8"},
{"value": "11f87"},
{"value": "dd7"},
{"value": "0"},
{"value": "f"},
{"value": "2231d"},
{"value": "40"},
{"value": "7194912"},
{"value": "3c2f4"},
{"value": "1678a0d6"},
{"value": "0"},
{"value": "17d46"},
{"value": "741"},
{"value": "d"},
{"value": "5c"},
{"value": "231727b3"},
{"value": "0"},
{"value": "73"},
{"value": "0"},
{"value": "3f"}
],
[
{"value": "b53d144"},
{"value": "7ffffff"},
{"value": "1fff"},
{"value": "c03b25"},
{"value": "b"},
{"value": "723fc7f"},
{"value": "3f1"},
{"value": "19afb"},
{"value": "121"},
{"value": "98ec5b4"},
{"value": "f63f71ab"},
{"value": "78c8"},
{"value": "11cc"},
{"value": "0"},
{"value": "21"},
{"value": "28877"},
{"value": "0"},
{"value": "36aca8c"},
{"value": "9df1"},
{"value": "f4d0a29"},
{"value": "0"},
{"value": "384e1"},
{"value": "465"},
{"value": "0"},
{"value": "5"},
{"value": "1973b2fc"},
{"value": "0"},
{"value": "21"},
{"value": "0"},
{"value": "67"}
],
[
{"value": "7c3a2c5"},
{"value": "115b8a9"},
{"value": "1fff"},
{"value": "7555fd"},
{"value": "e"},
{"value": "9e1188"},
{"value": "18c"},
{"value": "17afe"},
{"value": "190"},
{"value": "8f3c55d"},
{"value": "59964614"},
{"value": "61e63"},
{"value": "2fc8"},
{"value": "0"},
{"value": "aa"},
{"value": "28890"},
{"value": "80"},
{"value": "8aeeaac"},
{"value": "11aa9"},
{"value": "992588e"},
{"value": "0"},
{"value": "3dd9f"},
{"value": "771"},
{"value": "6"},
{"value": "5d"},
{"value": "3d979051"},
{"value": "0"},
{"value": "29"},
{"value": "0"},
{"value": "28"}
],
[
{"value": "1835355f"},
{"value": "516b7d5"},
{"value": "1fff"},
{"value": "a5a436"},
{"value": "7"},
{"value": "1374da5"},
{"value": "3be"},
{"value": "21e7"},
{"value": "808"},
{"value": "9305f618"},
{"value": "b4a6608d"},
{"value": "76326"},
{"value": "1681"},
{"value": "0"},
{"value": "a8"},
{"value": "b0c0"},
{"value": "0"},
{"value": "3b0a648"},
{"value": "e50d"},
{"value": "1ef384cc"},
{"value": "0"},
{"value": "3e9d7"},
{"value": "3fb"},
{"value": "5"},
{"value": "9"},
{"value": "3f861b89"},
{"value": "0"},
{"value": "1f"},
{"value": "0"},
{"value": "48"}
],
[
{"value": "110e241e"},
{"value": "44aacdb"},
{"value": "1fff"},
{"value": "866f12"},
{"value": "e"},
{"value": "cf4c12"},
{"value": "2bd"},
{"value": "4edf"},
{"value": "d43"},
{"value": "67b07740"},
{"value": "b82b5f82"},
{"value": "ffbad"},
{"value": "32b9"},
{"value": "0"},
{"value": "b2"},
{"value": "14d8c"},
{"value": "80"},
{"value": "54354a6"},
{"value": "3bd9"},
{"value": "168c6116"},
{"value": "0"},
{"value": "3fb3b"},
{"value": "6cb"},
{"value": "2"},
{"value": "28"},
{"value": "2f5b92b6"},
{"value": "0"},
{"value": "13"},
{"value": "0"},
{"value": "5f"}
],
[
{"value": "91f1491"},
{"value": "50160ad"},
{"value": "1fff"},
{"value": "757fe6"},
{"value": "9"},
{"value": "62fe914"},
{"value": "3a4"},
{"value": "7976"},
{"value": "9f3"},
{"value": "d08fc507"},
{"value": "a292793a"},
{"value": "9160d"},
{"value": "36e2"},
{"value": "0"},
{"value": "4d"},
{"value": "b61d"},
{"value": "0"},
{"value": "13fe3d76"},
{"value": "e1d9"},
{"value": "5611a57"},
{"value": "0"},
{"value": "238ec"},
{"value": "56"},
{"value": "8"},
{"value": "55"},
{"value": "3f9e78de"},
{"value": "0"},
{"value": "33"},
{"value": "0"},
{"value": "16"}
],
[
{"value": "5e29082"},
{"value": "4d7da1b"},
{"value": "1fff"},
{"value": "4448b4"},
{"value": "8"},
{"value": "7d95b37"},
{"value": "2a"},
{"value": "7dda"},
{"value": "caa"},
{"value": "d55fb983"},
{"value": "9595e64a"},
{"value": "5140c"},
{"value": "376a"},
{"value": "0"},
{"value": "a"},
{"value": "12b4e"},
{"value": "0"},
{"value": "122c7fea"},
{"value": "24426"},
{"value": "1e4742fc"},
{"value": "0"},
{"value": "3737c"},
{"value": "518"},
{"value": "5"},
{"value": "67"},
{"value": "e6ba879"},
{"value": "0"},
{"value": "52"},
{"value": "0"},
{"value": "69"}
],
[
{"value": "1fde06ee"},
{"value": "6b8b83b"},
{"value": "1fff"},
{"value": "c20f4f"},
{"value": "b"},
{"value": "6775ae7"},
{"value": "192"},
{"value": "8cd1"},
{"value": "30d"},
{"value": "1ea0621c"},
{"value": "f4e1365c"},
{"value": "44b69"},
{"value": "13ca"},
{"value": "0"},
{"value": "6f"},
{"value": "1edc1"},
{"value": "0"},
{"value": "996a56e"},
{"value": "133e3"},
{"value": "18c6a81c"},
{"value": "0"},
{"value": "355c2"},
{"value": "324"},
{"value": "5"},
{"value": "3f"},
{"value": "27e26d7d"},
{"value": "0"},
{"value": "10"},
{"value": "0"},
{"value": "5a"}
],
[
{"value": "114702d3"},
{"value": "2c26f56"},
{"value": "1fff"},
{"value": "c84f06"},
{"value": "9"},
{"value": "30fa373"},
{"value": "255"},
{"value": "10567"},
{"value": "edc"},
{"value": "a7523dfd"},
{"value": "a090244c"},
{"value": "63a37"},
{"value": "9b2"},
{"value": "0"},
{"value": "50"},
{"value": "2d82a"},
{"value": "0"},
{"value": "d7a1ed0"},
{"value": "1bc4d"},
{"value": "b5dbaef"},
{"value": "0"},
{"value": "1cd0d"},
{"value": "98"},
{"value": "8"},
{"value": "3"},
{"value": "2e27fec8"},
{"value": "0"},
{"value": "3a"},
{"value": "0"},
{"value": "3d"}
],
[
{"value": "16320532"},
{"value": "1e065db"},
{"value": "1fff"},
{"value": "e2534d"},
{"value": "9"},
{"value": "2c5cb33"},
{"value": "25f"},
{"value": "1af1e"},
{"value": "1b9"},
{"value": "bf8a8f46"},
{"value": "45bd4edf"},
{"value": "15a25d"},
{"value": "617"},
{"value": "0"},
{"value": "dc"},
{"value": "1e0e5"},
{"value": "0"},
{"value": "ef81e68"},
{"value": "2efca"},
{"value": "7181df1"},
{"value": "0"},
{"value": "2a0e1"},
{"value": "6f1"},
{"value": "1"},
{"value": "1f"},
{"value": "2deffc09"},
{"value": "0"},
{"value": "38"},
{"value": "0"},
{"value": "2d"}
],
[
{"value": "185cfe2d"},
{"value": "7180ea5"},
{"value": "1fff"},
{"value": "6cad2f"},
{"value": "f"},
{"value": "26b98b1"},
{"value": "129"},
{"value": "1e7a3"},
{"value": "a19"},
{"value": "a278d9e5"},
{"value": "690a453"},
{"value": "15ddde"},
{"value": "2e4a"},
{"value": "0"},
{"value": "8e"},
{"value": "1b7d5"},
{"value": "0"},
{"value": "1cfa8825"},
{"value": "d970"},
{"value": "1f625d77"},
{"value": "0"},
{"value": "30693"},
{"value": "4b6"},
{"value": "5"},
{"value": "36"},
{"value": "fead963"},
{"value": "0"},
{"value": "a"},
{"value": "0"},
{"value": "19"}
],
[
{"value": "5d2f796"},
{"value": "549163e"},
{"value": "1fff"},
{"value": "15e5df"},
{"value": "a"},
{"value": "50a8787"},
{"value": "3c8"},
{"value": "1a99f"},
{"value": "1b4"},
{"value": "55c8a6a9"},
{"value": "7486706"},
{"value": "17209e"},
{"value": "1d21"},
{"value": "0"},
{"value": "1d"},
{"value": "131de"},
{"value": "80"},
{"value": "e7f0aab"},
{"value": "195ab"},
{"value": "bcf3b70"},
{"value": "0"},
{"value": "10e33"},
{"value": "59a"},
{"value": "a"},
{"value": "3d"},
{"value": "cd9563e"},
{"value": "0"},
{"value": "31"},
{"value": "0"},
{"value": "46"}
],
[
{"value": "a5cb68c"},
{"value": "3fa6b11"},
{"value": "1fff"},
{"value": "f044a4"},
{"value": "a"},
{"value": "21d56de"},
{"value": "96"},
{"value": "c408"},
{"value": "c7"},
{"value": "c6641761"},
{"value": "e2d857af"},
{"value": "77e10"},
{"value": "7ac"},
{"value": "0"},
{"value": "d2"},
{"value": "2265f"},
{"value": "80"},
{"value": "106cf996"},
{"value": "12876"},
{"value": "14ca2fda"},
{"value": "0"},
{"value": "7b5d"},
{"value": "a7"},
{"value": "1"},
{"value": "2b"},
{"value": "22356513"},
{"value": "0"},
{"value": "3f"},
{"value": "0"},
{"value": "6e"}
],
[
{"value": "1f34846"},
{"value": "2510acc"},
{"value": "1fff"},
{"value": "ac9500"},
{"value": "d"},
{"value": "3fbdaca"},
{"value": "27d"},
{"value": "1b4bc"},
{"value": "5aa"},
{"value": "9272a81b"},
{"value": "7410fdce"},
{"value": "6e7f0"},
{"value": "6c"},
{"value": "0"},
{"value": "63"},
{"value": "7d0a"},
{"value": "0"},
{"value": "fd1bfa1"},
{"value": "92bd"},
{"value": "f0e8e0a"},
{"value": "0"},
{"value": "63ca"},
{"value": "1e"},
{"value": "7"},
{"value": "4"},
{"value": "1fde4834"},
{"value": "0"},
{"value": "3d"},
{"value": "0"},
{"value": "66"}
],
[
{"value": "1f4333c8"},
{"value": "18d6562"},
{"value": "1fff"},
{"value": "d1a4d1"},
{"value": "3"},
{"value": "10f124f"},
{"value": "60"},
{"value": "6773"},
{"value": "8fb"},
{"value": "6c09733e"},
{"value": "527818ea"},
{"value": "1e2a0"},
{"value": "88d"},
{"value": "0"},
{"value": "2c"},
{"value": "14abb"},
{"value": "0"},
{"value": "13088240"},
{"value": "261a8"},
{"value": "7fd97c3"},
{"value": "0"},
{"value": "16730"},
{"value": "398"},
{"value": "6"},
{"value": "54"},
{"value": "2feb9b6b"},
{"value": "0"},
{"value": "56"},
{"value": "0"},
{"value": "34"}
],
[
{"value": "1ea5ef5c"},
{"value": "e2b213"},
{"value": "1fff"},
{"value": "92ab55"},
{"value": "f"},
{"value": "71d8043"},
{"value": "3ee"},
{"value": "7a69"},
{"value": "cbd"},
{"value": "9d31bee1"},
{"value": "4354d31"},
{"value": "9a867"},
{"value": "244"},
{"value": "0"},
{"value": "51"},
{"value": "693f"},
{"value": "0"},
{"value": "81a2b79"},
{"value": "38e69"},
{"value": "848c482"},
{"value": "0"},
{"value": "2e577"},
{"value": "33b"},
{"value": "6"},
{"value": "39"},
{"value": "6c17be2"},
{"value": "0"},
{"value": "5f"},
{"value": "0"},
{"value": "74"}
],
[
{"value": "1f5b02c1"},
{"value": "71013c3"},
{"value": "1fff"},
{"value": "619526"},
{"value": "e"},
{"value": "2c87341"},
{"value": "144"},
{"value": "d37"},
{"value": "401"},
{"value": "8eda35a"},
{"value": "ac29596e"},
{"value": "dd974"},
{"value": "3e1e"},
{"value": "0"},
{"value": "e1"},
{"value": "b8f0"},
{"value": "0"},
{"value": "1e37a5e6"},
{"value": "3756"},
{"value": "1aa3baf9"},
{"value": "0"},
{"value": "61b7"},
{"value": "2d"},
{"value": "a"},
{"value": "28"},
{"value": "6bbf1ee"},
{"value": "0"},
{"value": "1"},
{"value": "0"},
{"value": "1"}
],
[
{"value": "1eda1e7"},
{"value": "7659180"},
{"value": "1fff"},
{"value": "a6ab6c"},
{"value": "4"},
{"value": "6cd9260"},
{"value": "1f"},
{"value": "18a24"},
{"value": "58a"},
{"value": "ef7233"},
{"value": "e7a86256"},
{"value": "ff366"},
{"value": "14f9"},
{"value": "0"},
{"value": "b5"},
{"value": "3d20f"},
{"value": "c0"},
{"value": "1c9885b1"},
{"value": "24eb1"},
{"value": "1eee840d"},
{"value": "0"},
{"value": "2c90f"},
{"value": "3a5"},
{"value": "f"},
{"value": "77"},
{"value": "16344bb6"},
{"value": "0"},
{"value": "4f"},
{"value": "0"},
{"value": "69"}
],
[
{"value": "190668ed"},
{"value": "105cc81"},
{"value": "1fff"},
{"value": "b1ca1f"},
{"value": "f"},
{"value": "28699d"},
{"value": "35a"},
{"value": "2051"},
{"value": "3f1"},
{"value": "5ca7ac6e"},
{"value": "fa08a132"},
{"value": "1c8af0"},
{"value": "1e05"},
{"value": "0"},
{"value": "c5"},
{"value": "3b329"},
{"value": "0"},
{"value": "741a105"},
{"value": "1efda"},
{"value": "27dcf47"},
{"value": "0"},
{"value": "105d9"},
{"value": "7a2"},
{"value": "8"},
{"value": "40"},
{"value": "3f2667da"},
{"value": "0"},
{"value": "7a"},
{"value": "0"},
{"value": "b"}
],
[
{"value": "607d24d"},
{"value": "12c1ba1"},
{"value": "1fff"},
{"value": "2ee180"},
{"value": "5"},
{"value": "6cbed75"},
{"value": "303"},
{"value": "4df6"},
{"value": "7c1"},
{"value": "eaea1b7a"},
{"value": "4f2ead49"},
{"value": "88e33"},
{"value": "1db1"},
{"value": "0"},
{"value": "a0"},
{"value": "1ae5b"},
{"value": "0"},
{"value": "1d7128a8"},
{"value": "2f6d2"},
{"value": "1ab4d7a9"},
{"value": "0"},
{"value": "d2ab"},
{"value": "774"},
{"value": "e"},
{"value": "71"},
{"value": "12fc9bc3"},
{"value": "0"},
{"value": "5b"},
{"value": "0"},
{"value": "1f"}
],
[
{"value": "464043f"},
{"value": "4521a3"},
{"value": "1fff"},
{"value": "d1772b"},
{"value": "9"},
{"value": "9025e6"},
{"value": "15f"},
{"value": "75a2"},
{"value": "dde"},
{"value": "41b5e954"},
{"value": "555f9f11"},
{"value": "109e9f"},
{"value": "3b80"},
{"value": "0"},
{"value": "7b"},
{"value": "23f7c"},
{"value": "0"},
{"value": "a1ee6a3"},
{"value": "2cf8a"},
{"value": "ab97100"},
{"value": "0"},
{"value": "2e02b"},
{"value": "2c2"},
{"value": "5"},
{"value": "4b"},
{"value": "2b526c3"},
{"value": "0"},
{"value": "7"},
{"value": "0"},
{"value": "33"}
],
[
{"value": "1d0584ae"},
{"value": "231be92"},
{"value": "1fff"},
{"value": "84fbb3"},
{"value": "3"},
{"value": "57a8d8e"},
{"value": "3"},
{"value": "925c"},
{"value": "456"},
{"value": "257ecb42"},
{"value": "88e81fb5"},
{"value": "13a81d"},
{"value": "3f9f"},
{"value": "0"},
{"value": "65"},
{"value": "117a1"},
{"value": "0"},
{"value": "502dade"},
{"value": "3c14e"},
{"value": "1081bebb"},
{"value": "0"},
{"value": "370f7"},
{"value": "3d9"},
{"value": "5"},
{"value": "74"},
{"value": "1860c64b"},
{"value": "0"},
{"value": "35"},
{"value": "0"},
{"value": "16"}
],
[
{"value": "1c73cda6"},
{"value": "26fbb8e"},
{"value": "1fff"},
{"value": "349e1e"},
{"value": "a"},
{"value": "9ce4f0"},
{"value": "a2"},
{"value": "725b"},
{"value": "79d"},
{"value": "f23906bb"},
{"value": "a4d9ff45"},
{"value": "474ac"},
{"value": "17d8"},
{"value": "0"},
{"value": "12"},
{"value": "e06"},
{"value": "0"},
{"value": "11eebc56"},
{"value": "2cfa6"},
{"value": "1ea9ab07"},
{"value": "0"},
{"value": "104da"},
{"value": "39f"},
{"value": "2"},
{"value": "46"},
{"value": "3dd64dd8"},
{"value": "0"},
{"value": "3b"},
{"value": "0"},
{"value": "73"}
],
[
{"value": "a857959"},
{"value": "1ec37c"},
{"value": "1fff"},
{"value": "7614e"},
{"value": "e"},
{"value": "4c9aba7"},
{"value": "c1"},
{"value": "7157"},
{"value": "4c5"},
{"value": "1ccf1865"},
{"value": "718b68a6"},
{"value": "1e796b"},
{"value": "582"},
{"value": "0"},
{"value": "80"},
{"value": "1ae10"},
{"value": "80"},
{"value": "114964c9"},
{"value": "342a4"},
{"value": "2c8af7a"},
{"value": "0"},
{"value": "3bd12"},
{"value": "1e4"},
{"value": "8"},
{"value": "34"},
{"value": "ff3da98"},
{"value": "0"},
{"value": "41"},
{"value": "0"},
{"value": "43"}
],
[
{"value": "15703f4a"},
{"value": "7c3f1ff"},
{"value": "1fff"},
{"value": "40e40d"},
{"value": "3"},
{"value": "3a3f43b"},
{"value": "ce"},
{"value": "15b52"},
{"value": "8fd"},
{"value": "42211e84"},
{"value": "6503db35"},
{"value": "1a23eb"},
{"value": "249"},
{"value": "0"},
{"value": "f3"},
{"value": "349a"},
{"value": "0"},
{"value": "33e552"},
{"value": "2f37c"},
{"value": "117f1b81"},
{"value": "0"},
{"value": "37b3f"},
{"value": "62e"},
{"value": "6"},
{"value": "71"},
{"value": "3a070be6"},
{"value": "0"},
{"value": "15"},
{"value": "0"},
{"value": "6f"}
],
[
{"value": "17c38977"},
{"value": "6935b9d"},
{"value": "1fff"},
{"value": "e87d29"},
{"value": "9"},
{"value": "7bca178"},
{"value": "cc"},
{"value": "806b"},
{"value": "9ae"},
{"value": "ab7129c2"},
{"value": "2588393d"},
{"value": "6cc57"},
{"value": "1153"},
{"value": "0"},
{"value": "d8"},
{"value": "16d4c"},
{"value": "0"},
{"value": "40eadc3"},
{"value": "9f46"},
{"value": "18a19252"},
{"value": "0"},
{"value": "39e3d"},
{"value": "63c"},
{"value": "7"},
{"value": "73"},
{"value": "23d03e85"},
{"value": "0"},
{"value": "21"},
{"value": "0"},
{"value": "35"}
],
[
{"value": "e5350d9"},
{"value": "51cba15"},
{"value": "1fff"},
{"value": "4a16e5"},
{"value": "8"},
{"value": "4c3ad9e"},
{"value": "1bd"},
{"value": "1e57d"},
{"value": "291"},
{"value": "8941fce0"},
{"value": "dc67952"},
{"value": "141d0e"},
{"value": "938"},
{"value": "0"},
{"value": "ea"},
{"value": "1f455"},
{"value": "a0"},
{"value": "371ee4e"},
{"value": "17277"},
{"value": "8fc4ac"},
{"value": "0"},
{"value": "24ff"},
{"value": "6fc"},
{"value": "c"},
{"value": "18"},
{"value": "16ce6423"},
{"value": "0"},
{"value": "57"},
{"value": "0"},
{"value": "42"}
],
[
{"value": "19f85273"},
{"value": "7ffffff"},
{"value": "1fff"},
{"value": "e3e1a2"},
{"value": "3"},
{"value": "51674f0"},
{"value": "5"},
{"value": "e5d0"},
{"value": "914"},
{"value": "e12e6231"},
{"value": "52d274c1"},
{"value": "1a9f12"},
{"value": "1f0e"},
{"value": "0"},
{"value": "65"},
{"value": "c0e2"},
{"value": "0"},
{"value": "5407300"},
{"value": "1e8a1"},
{"value": "1308471a"},
{"value": "0"},
{"value": "3d3bd"},
{"value": "4d6"},
{"value": "0"},
{"value": "60"},
{"value": "2cb13c7a"},
{"value": "0"},
{"value": "1e"},
{"value": "0"},
{"value": "6"}
],
[
{"value": "3a10cda"},
{"value": "2eddec7"},
{"value": "1fff"},
{"value": "bfeea2"},
{"value": "7"},
{"value": "5b76ff9"},
{"value": "7a"},
{"value": "c2bd"},
{"value": "994"},
{"value": "c7dc7374"},
{"value": "4d826557"},
{"value": "a1ea6"},
{"value": "33a2"},
{"value": "0"},
{"value": "a0"},
{"value": "2a2f7"},
{"value": "0"},
{"value": "475ef8c"},
{"value": "11f89"},
{"value": "11863442"},
{"value": "0"},
{"value": "376c9"},
{"value": "403"},
{"value": "f"},
{"value": "12"},
{"value": "3e6d0aab"},
{"value": "0"},
{"value": "c"},
{"value": "0"},
{"value": "6b"}
],
[
{"value": "1fdfd181"},
{"value": "6746558"},
{"value": "1fff"},
{"value": "40df22"},
{"value": "b"},
{"value": "72dd025"},
{"value": "311"},
{"value": "1d317"},
{"value": "c75"},
{"value": "daa6724b"},
{"value": "652046c7"},
{"value": "180d64"},
{"value": "61a"},
{"value": "0"},
{"value": "13"},
{"value": "17e38"},
{"value": "0"},
{"value": "1d2697cd"},
{"value": "11502"},
{"value": "12df8fd3"},
{"value": "0"},
{"value": "3e5a4"},
{"value": "7ae"},
{"value": "b"},
{"value": "4a"},
{"value": "5cea99a"},
{"value": "0"},
{"value": "34"},
{"value": "0"},
{"value": "54"}
],
[
{"value": "d505894"},
{"value": "1b6f524"},
{"value": "1fff"},
{"value": "b24043"},
{"value": "9"},
{"value": "1da050f"},
{"value": "205"},
{"value": "3755"},
{"value": "e40"},
{"value": "54464e4c"},
{"value": "90faf2ce"},
{"value": "11cf49"},
{"value": "4"},
{"value": "0"},
{"value": "fc"},
{"value": "391bb"},
{"value": "0"},
{"value": "14405af6"},
{"value": "2d92b"},
{"value": "cc6d1b4"},
{"value": "0"},
{"value": "2f8ef"},
{"value": "757"},
{"value": "3"},
{"value": "38"},
{"value": "2ee1f8db"},
{"value": "0"},
{"value": "31"},
{"value": "0"},
{"value": "9"}
],
[
{"value": "9680af1"},
{"value": "88bc20"},
{"value": "1fff"},
{"value": "14d2"},
{"value": "f"},
{"value": "2697198"},
{"value": "32f"},
{"value": "ff7c"},
{"value": "437"},
{"value": "97c9dc5"},
{"value": "7bf70e45"},
{"value": "66061"},
{"value": "b80"},
{"value": "0"},
{"value": "d2"},
{"value": "19bc6"},
{"value": "0"},
{"value": "9dcb6e9"},
{"value": "c74a"},
{"value": "1ab7fc4c"},
{"value": "0"},
{"value": "452"},
{"value": "4c"},
{"value": "4"},
{"value": "2"},
{"value": "3fb15caf"},
{"value": "0"},
{"value": "71"},
{"value": "0"},
{"value": "1c"}
],
[
{"value": "1933b323"},
{"value": "63dea96"},
{"value": "1fff"},
{"value": "7f425f"},
{"value": "8"},
{"value": "580de69"},
{"value": "1f1"},
{"value": "27ba"},
{"value": "e5f"},
{"value": "1931232f"},
{"value": "494de39f"},
{"value": "195b30"},
{"value": "d8a"},
{"value": "0"},
{"value": "42"},
{"value": "e694"},
{"value": "60"},
{"value": "e39fb48"},
{"value": "29016"},
{"value": "3946dc4"},
{"value": "0"},
{"value": "37209"},
{"value": "658"},
{"value": "a"},
{"value": "24"},
{"value": "2c03a48e"},
{"value": "0"},
{"value": "56"},
{"value": "0"},
{"value": "74"}
],
[
{"value": "16b60004"},
{"value": "2fae7be"},
{"value": "1fff"},
{"value": "a294d5"},
{"value": "7"},
{"value": "1e3a89f"},
{"value": "310"},
{"value": "13756"},
{"value": "358"},
{"value": "2d76dc26"},
{"value": "748da5fb"},
{"value": "19678f"},
{"value": "343c"},
{"value": "0"},
{"value": "84"},
{"value": "244bc"},
{"value": "0"},
{"value": "1b844fcb"},
{"value": "1cf5a"},
{"value": "5364a30"},
{"value": "0"},
{"value": "3190"},
{"value": "302"},
{"value": "9"},
{"value": "21"},
{"value": "260c2d3a"},
{"value": "0"},
{"value": "47"},
{"value": "0"},
{"value": "2b"}
],
[
{"value": "1ca732c1"},
{"value": "2632adf"},
{"value": "1fff"},
{"value": "ebea59"},
{"value": "9"},
{"value": "356f52b"},
{"value": "2b2"},
{"value": "f764"},
{"value": "85e"},
{"value": "da799752"},
{"value": "3961c24c"},
{"value": "1051aa"},
{"value": "c63"},
{"value": "0"},
{"value": "9d"},
{"value": "facd"},
{"value": "0"},
{"value": "17d0e476"},
{"value": "16a8b"},
{"value": "917d98d"},
{"value": "0"},
{"value": "414f"},
{"value": "350"},
{"value": "9"},
{"value": "2b"},
{"value": "1c91091"},
{"value": "0"},
{"value": "78"},
{"value": "0"},
{"value": "61"}
],
[
{"value": "9ea022f"},
{"value": "6426da6"},
{"value": "1fff"},
{"value": "fb1770"},
{"value": "8"},
{"value": "67de097"},
{"value": "332"},
{"value": "9ba2"},
{"value": "30a"},
{"value": "aae6fa4f"},
{"value": "7a2a2341"},
{"value": "1c8e8d"},
{"value": "1896"},
{"value": "0"},
{"value": "2a"},
{"value": "22e9c"},
{"value": "a0"},
{"value": "ab3f16f"},
{"value": "2cbd3"},
{"value": "ee847b4"},
{"value": "0"},
{"value": "62f2"},
{"value": "35b"},
{"value": "e"},
{"value": "23"},
{"value": "352be3eb"},
{"value": "0"},
{"value": "4e"},
{"value": "0"},
{"value": "1e"}
],
[
{"value": "1596978a"},
{"value": "2ae5f66"},
{"value": "1fff"},
{"value": "e0fdaa"},
{"value": "9"},
{"value": "5fe41e2"},
{"value": "353"},
{"value": "3586"},
{"value": "b1b"},
{"value": "6551f6a1"},
{"value": "b1be52b2"},
{"value": "1a9c9b"},
{"value": "1b9f"},
{"value": "0"},
{"value": "c5"},
{"value": "21158"},
{"value": "0"},
{"value": "a9fbfc8"},
{"value": "1b895"},
{"value": "104dc52b"},
{"value": "0"},
{"value": "2b70d"},
{"value": "2f6"},
{"value": "f"},
{"value": "38"},
{"value": "3df61ae1"},
{"value": "0"},
{"value": "64"},
{"value": "0"},
{"value": "5b"}
],
[
{"value": "189b97f8"},
{"value": "6e33c56"},
{"value": "1fff"},
{"value": "6a3961"},
{"value": "8"},
{"value": "50fad99"},
{"value": "349"},
{"value": "10fca"},
{"value": "a15"},
{"value": "bf2d7157"},
{"value": "901b2490"},
{"value": "61a0c"},
{"value": "2aac"},
{"value": "0"},
{"value": "2f"},
{"value": "20368"},
{"value": "60"},
{"value": "1f3fffc8"},
{"value": "29791"},
{"value": "1b4bc974"},
{"value": "0"},
{"value": "b739"},
{"value": "2e"},
{"value": "6"},
{"value": "34"},
{"value": "52ef46d"},
{"value": "0"},
{"value": "1d"},
{"value": "0"},
{"value": "1e"}
],
[
{"value": "e405058"},
{"value": "26c4ed0"},
{"value": "1fff"},
{"value": "b35fcb"},
{"value": "a"},
{"value": "4259c93"},
{"value": "c4"},
{"value": "1a0ce"},
{"value": "60b"},
{"value": "ff1e7b8d"},
{"value": "b485e99c"},
{"value": "d304d"},
{"value": "1057"},
{"value": "0"},
{"value": "83"},
{"value": "1b717"},
{"value": "0"},
{"value": "4a8dcd8"},
{"value": "35d92"},
{"value": "5b9e3df"},
{"value": "0"},
{"value": "24ad2"},
{"value": "6ed"},
{"value": "6"},
{"value": "43"},
{"value": "22f5f989"},
{"value": "0"},
{"value": "73"},
{"value": "0"},
{"value": "5c"}
],
[
{"value": "135868ac"},
{"value": "644a036"},
{"value": "1fff"},
{"value": "68fde"},
{"value": "6"},
{"value": "4bb6b2b"},
{"value": "c6"},
{"value": "9edb"},
{"value": "e0f"},
{"value": "d3fa5f56"},
{"value": "60ba0a3d"},
{"value": "13686"},
{"value": "1c46"},
{"value": "0"},
{"value": "95"},
{"value": "2a291"},
{"value": "0"},
{"value": "15eda855"},
{"value": "2488c"},
{"value": "1247638e"},
{"value": "0"},
{"value": "24d63"},
{"value": "454"},
{"value": "1"},
{"value": "3"},
{"value": "2d14234c"},
{"value": "0"},
{"value": "41"},
{"value": "0"},
{"value": "9"}
],
[
{"value": "900e2a7"},
{"value": "51e8fa8"},
{"value": "1fff"},
{"value": "fcb30d"},
{"value": "c"},
{"value": "5a51e39"},
{"value": "a3"},
{"value": "a066"},
{"value": "b7a"},
{"value": "5ffea039"},
{"value": "4df0cfe1"},
{"value": "1baf8e"},
{"value": "2030"},
{"value": "0"},
{"value": "86"},
{"value": "f2a6"},
{"value": "80"},
{"value": "87493c6"},
{"value": "1793a"},
{"value": "1f4151ea"},
{"value": "0"},
{"value": "369a"},
{"value": "6fe"},
{"value": "e"},
{"value": "3b"},
{"value": "1de5ff71"},
{"value": "0"},
{"value": "1a"},
{"value": "0"},
{"value": "46"}
],
[
{"value": "b1673ed"},
{"value": "23f0ae2"},
{"value": "1fff"},
{"value": "6e9bb1"},
{"value": "9"},
{"value": "8045c1"},
{"value": "191"},
{"value": "a77f"},
{"value": "204"},
{"value": "514d0303"},
{"value": "a74e71b5"},
{"value": "6f694"},
{"value": "1e7a"},
{"value": "0"},
{"value": "25"},
{"value": "2d8fc"},
{"value": "0"},
{"value": "663fa8"},
{"value": "1ff16"},
{"value": "6383ebb"},
{"value": "0"},
{"value": "24c7a"},
{"value": "3f1"},
{"value": "8"},
{"value": "5b"},
{"value": "fd5b51e"},
{"value": "0"},
{"value": "16"},
{"value": "0"},
{"value": "52"}
],
[
{"value": "6dfd90b"},
{"value": "2be559c"},
{"value": "1fff"},
{"value": "25c7c9"},
{"value": "2"},
{"value": "79e0dd8"},
{"value": "a5"},
{"value": "901b"},
{"value": "bc6"},
{"value": "bbba485d"},
{"value": "e8b834e0"},
{"value": "c9da1"},
{"value": "1000"},
{"value": "0"},
{"value": "d5"},
{"value": "e858"},
{"value": "80"},
{"value": "13dd5496"},
{"value": "2b3cb"},
{"value": "8eac8a5"},
{"value": "0"},
{"value": "1994d"},
{"value": "5cd"},
{"value": "c"},
{"value": "62"},
{"value": "3d5fd903"},
{"value": "0"},
{"value": "32"},
{"value": "0"},
{"value": "14"}
],
[
{"value": "99071a6"},
{"value": "34f75d9"},
{"value": "1fff"},
{"value": "d1f67"},
{"value": "8"},
{"value": "758c8f3"},
{"value": "31e"},
{"value": "6e48"},
{"value": "6bf"},
{"value": "20707e9f"},
{"value": "f13d33ef"},
{"value": "12aec6"},
{"value": "36f2"},
{"value": "0"},
{"value": "34"},
{"value": "2ff1d"},
{"value": "20"},
{"value": "1612444b"},
{"value": "148a9"},
{"value": "1d28b94a"},
{"value": "0"},
{"value": "3d65b"},
{"value": "5fe"},
{"value": "5"},
{"value": "60"},
{"value": "1a576c4e"},
{"value": "0"},
{"value": "13"},
{"value": "0"},
{"value": "29"}
],
[
{"value": "fd2f76f"},
{"value": "b3f61c"},
{"value": "1fff"},
{"value": "60594"},
{"value": "8"},
{"value": "219b341"},
{"value": "1eb"},
{"value": "12534"},
{"value": "15e"},
{"value": "a320405a"},
{"value": "79efad1a"},
{"value": "1e73d1"},
{"value": "159a"},
{"value": "0"},
{"value": "5"},
{"value": "3445c"},
{"value": "0"},
{"value": "14734cb0"},
{"value": "abe8"},
{"value": "60cd32"},
{"value": "0"},
{"value": "2e71b"},
{"value": "6a7"},
{"value": "8"},
{"value": "15"},
{"value": "147fe9f4"},
{"value": "0"},
{"value": "41"},
{"value": "0"},
{"value": "3"}
],
[
{"value": "fa7e5cc"},
{"value": "522de8b"},
{"value": "1fff"},
{"value": "d4b173"},
{"value": "3"},
{"value": "18122da"},
{"value": "28b"},
{"value": "10af4"},
{"value": "148"},
{"value": "2b24358a"},
{"value": "c3e4d9ef"},
{"value": "d8ee5"},
{"value": "1ea0"},
{"value": "0"},
{"value": "a6"},
{"value": "3bd25"},
{"value": "0"},
{"value": "554c424"},
{"value": "31e0b"},
{"value": "b20dfcf"},
{"value": "0"},
{"value": "1061e"},
{"value": "501"},
{"value": "f"},
{"value": "77"},
{"value": "2fa0869"},
{"value": "0"},
{"value": "1f"},
{"value": "0"},
{"value": "12"}
],
[
{"value": "3d442c3"},
{"value": "65534f6"},
{"value": "1fff"},
{"value": "c053d3"},
{"value": "8"},
{"value": "59d0e54"},
{"value": "1c5"},
{"value": "3eec"},
{"value": "bac"},
{"value": "8a632532"},
{"value": "60c2f4b"},
{"value": "1ed46b"},
{"value": "c93"},
{"value": "0"},
{"value": "a5"},
{"value": "1a0d0"},
{"value": "60"},
{"value": "1915b7d0"},
{"value": "38153"},
{"value": "19c194ed"},
{"value": "0"},
{"value": "26232"},
{"value": "503"},
{"value": "1"},
{"value": "53"},
{"value": "26c280d"},
{"value": "0"},
{"value": "4e"},
{"value": "0"},
{"value": "31"}
],
[
{"value": "7b5c3c6"},
{"value": "a8fa8d"},
{"value": "1fff"},
{"value": "a8b49b"},
{"value": "a"},
{"value": "637f465"},
{"value": "2a2"},
{"value": "492f"},
{"value": "b7b"},
{"value": "7c7f0e1e"},
{"value": "ba6dde35"},
{"value": "82d1"},
{"value": "a4d"},
{"value": "0"},
{"value": "3"},
{"value": "102be"},
{"value": "0"},
{"value": "6f7fd06"},
{"value": "34068"},
{"value": "5352447"},
{"value": "0"},
{"value": "2d253"},
{"value": "d5"},
{"value": "e"},
{"value": "b"},
{"value": "331233a1"},
{"value": "0"},
{"value": "3f"},
{"value": "0"},
{"value": "24"}
],
[
{"value": "11af9215"},
{"value": "720d8b2"},
{"value": "1fff"},
{"value": "b93946"},
{"value": "8"},
{"value": "94b9a5"},
{"value": "a3"},
{"value": "f30b"},
{"value": "f5c"},
{"value": "bef37c72"},
{"value": "1faa37b1"},
{"value": "194380"},
{"value": "16d8"},
{"value": "0"},
{"value": "63"},
{"value": "1ff99"},
{"value": "80"},
{"value": "1cea180e"},
{"value": "35d4"},
{"value": "142da45"},
{"value": "0"},
{"value": "d6e9"},
{"value": "2e8"},
{"value": "1"},
{"value": "4"},
{"value": "340f65e1"},
{"value": "0"},
{"value": "3b"},
{"value": "0"},
{"value": "6d"}
],
[
{"value": "1f9bfd34"},
{"value": "7d49e06"},
{"value": "1fff"},
{"value": "fc069e"},
{"value": "b"},
{"value": "1298d63"},
{"value": "2c4"},
{"value": "c45b"},
{"value": "edd"},
{"value": "8587a268"},
{"value": "dba5de8c"},
{"value": "18e8b1"},
{"value": "218a"},
{"value": "0"},
{"value": "a4"},
{"value": "3d006"},
{"value": "0"},
{"value": "a69f376"},
{"value": "7f53"},
{"value": "1ec2d0a6"},
{"value": "0"},
{"value": "15f3f"},
{"value": "cf"},
{"value": "8"},
{"value": "1a"},
{"value": "14467582"},
{"value": "0"},
{"value": "22"},
{"value": "0"},
{"value": "e"}
],
[
{"value": "a69bd1f"},
{"value": "5c408c9"},
{"value": "1fff"},
{"value": "113b3c"},
{"value": "9"},
{"value": "60dc368"},
{"value": "cc"},
{"value": "1ef3d"},
{"value": "50f"},
{"value": "c94c4a64"},
{"value": "b8c9008d"},
{"value": "180572"},
{"value": "2b76"},
{"value": "0"},
{"value": "88"},
{"value": "2d433"},
{"value": "0"},
{"value": "1f37e144"},
{"value": "c607"},
{"value": "117881bb"},
{"value": "0"},
{"value": "2eeed"},
{"value": "3ea"},
{"value": "3"},
{"value": "31"},
{"value": "495def4"},
{"value": "0"},
{"value": "43"},
{"value": "0"},
{"value": "5f"}
],
[
{"value": "c327d2f"},
{"value": "1af17dc"},
{"value": "1fff"},
{"value": "3f7961"},
{"value": "e"},
{"value": "77dfb33"},
{"value": "271"},
{"value": "16d52"},
{"value": "aa8"},
{"value": "59e9f66"},
{"value": "9caa7221"},
{"value": "c8c2f"},
{"value": "135e"},
{"value": "0"},
{"value": "eb"},
{"value": "32318"},
{"value": "80"},
{"value": "b6b090a"},
{"value": "12585"},
{"value": "136b4dc5"},
{"value": "0"},
{"value": "24441"},
{"value": "3c5"},
{"value": "d"},
{"value": "52"},
{"value": "39e34f72"},
{"value": "0"},
{"value": "26"},
{"value": "0"},
{"value": "1"}
],
[
{"value": "c8fb27f"},
{"value": "2761d7f"},
{"value": "1fff"},
{"value": "34536f"},
{"value": "f"},
{"value": "70856da"},
{"value": "8d"},
{"value": "3a94"},
{"value": "8b4"},
{"value": "f90ff2"},
{"value": "5b1894b1"},
{"value": "a74e6"},
{"value": "196d"},
{"value": "0"},
{"value": "fb"},
{"value": "3f1f8"},
{"value": "0"},
{"value": "c929b6e"},
{"value": "f5c0"},
{"value": "e3f44cc"},
{"value": "0"},
{"value": "158dc"},
{"value": "20b"},
{"value": "e"},
{"value": "32"},
{"value": "1181845f"},
{"value": "0"},
{"value": "e"},
{"value": "0"},
{"value": "58"}
],
[
{"value": "12e79994"},
{"value": "53d229"},
{"value": "1fff"},
{"value": "30ddfd"},
{"value": "3"},
{"value": "519ab66"},
{"value": "215"},
{"value": "11751"},
{"value": "9d1"},
{"value": "2f3b79ba"},
{"value": "256b1d51"},
{"value": "1bcc96"},
{"value": "3765"},
{"value": "0"},
{"value": "8b"},
{"value": "f4d6"},
{"value": "0"},
{"value": "1cb8937f"},
{"value": "c13f"},
{"value": "176d1aad"},
{"value": "0"},
{"value": "29165"},
{"value": "5b0"},
{"value": "1"},
{"value": "6c"},
{"value": "e45b980"},
{"value": "0"},
{"value": "59"},
{"value": "0"},
{"value": "66"}
],
[
{"value": "4b3e6b9"},
{"value": "4045608"},
{"value": "1fff"},
{"value": "276e2e"},
{"value": "3"},
{"value": "22fdefe"},
{"value": "341"},
{"value": "186af"},
{"value": "64b"},
{"value": "a525277"},
{"value": "aa42c161"},
{"value": "c60dc"},
{"value": "275a"},
{"value": "0"},
{"value": "64"},
{"value": "3eb1a"},
{"value": "0"},
{"value": "dd7896"},
{"value": "b559"},
{"value": "187a2e4c"},
{"value": "0"},
{"value": "ac9c"},
{"value": "418"},
{"value": "9"},
{"value": "c"},
{"value": "3ec49c38"},
{"value": "0"},
{"value": "2f"},
{"value": "0"},
{"value": "6"}
],
[
{"value": "c4e573d"},
{"value": "7f967fa"},
{"value": "1fff"},
{"value": "cbe367"},
{"value": "c"},
{"value": "312d38a"},
{"value": "113"},
{"value": "16e9b"},
{"value": "7c5"},
{"value": "de49668d"},
{"value": "eff1f362"},
{"value": "11baa5"},
{"value": "1c69"},
{"value": "0"},
{"value": "7b"},
{"value": "8f56"},
{"value": "80"},
{"value": "10e1e4f2"},
{"value": "289da"},
{"value": "15308d8b"},
{"value": "0"},
{"value": "34a87"},
{"value": "67"},
{"value": "d"},
{"value": "4a"},
{"value": "7c6ec86"},
{"value": "0"},
{"value": "41"},
{"value": "0"},
{"value": "f"}
],
[
{"value": "e31365d"},
{"value": "7d82d5e"},
{"value": "1fff"},
{"value": "a08170"},
{"value": "3"},
{"value": "1ad497"},
{"value": "1ca"},
{"value": "4859"},
{"value": "38d"},
{"value": "bc6ec183"},
{"value": "6b405bec"},
{"value": "194e46"},
{"value": "1474"},
{"value": "0"},
{"value": "3b"},
{"value": "179c6"},
{"value": "0"},
{"value": "15b8fbea"},
{"value": "d71b"},
{"value": "9c6af85"},
{"value": "0"},
{"value": "1f8ff"},
{"value": "6bb"},
{"value": "e"},
{"value": "4f"},
{"value": "3fccddd6"},
{"value": "0"},
{"value": "4d"},
{"value": "0"},
{"value": "34"}
],
[
{"value": "9d2bc23"},
{"value": "3c62f2f"},
{"value": "1fff"},
{"value": "66927"},
{"value": "8"},
{"value": "1ee4207"},
{"value": "3ad"},
{"value": "3d4b"},
{"value": "bf3"},
{"value": "edc2a72a"},
{"value": "8fd8bf14"},
{"value": "1a2d8c"},
{"value": "3977"},
{"value": "0"},
{"value": "7a"},
{"value": "3b023"},
{"value": "40"},
{"value": "7543d1"},
{"value": "1dfa2"},
{"value": "a5bab58"},
{"value": "0"},
{"value": "36052"},
{"value": "25c"},
{"value": "6"},
{"value": "66"},
{"value": "3aa368af"},
{"value": "0"},
{"value": "23"},
{"value": "0"},
{"value": "5e"}
],
[
{"value": "1b9c0192"},
{"value": "1efb57"},
{"value": "1fff"},
{"value": "baf5f8"},
{"value": "a"},
{"value": "32aba6b"},
{"value": "371"},
{"value": "5d9e"},
{"value": "82a"},
{"value": "c36b52b8"},
{"value": "38e1290c"},
{"value": "c0dcc"},
{"value": "2c2e"},
{"value": "0"},
{"value": "ec"},
{"value": "14807"},
{"value": "0"},
{"value": "e91e821"},
{"value": "b84e"},
{"value": "194e719b"},
{"value": "0"},
{"value": "3b467"},
{"value": "5c4"},
{"value": "7"},
{"value": "e"},
{"value": "288fc46a"},
{"value": "0"},
{"value": "67"},
{"value": "0"},
{"value": "3a"}
],
[
{"value": "10c2e995"},
{"value": "c01d4"},
{"value": "1fff"},
{"value": "c60671"},
{"value": "4"},
{"value": "6f86c82"},
{"value": "1d3"},
{"value": "cf2"},
{"value": "493"},
{"value": "eb5b8c0b"},
{"value": "9951a35f"},
{"value": "fc122"},
{"value": "352e"},
{"value": "0"},
{"value": "93"},
{"value": "2a4e6"},
{"value": "40"},
{"value": "13d4c286"},
{"value": "3520e"},
{"value": "17050c64"},
{"value": "0"},
{"value": "34c00"},
{"value": "455"},
{"value": "a"},
{"value": "44"},
{"value": "1a6bc3e9"},
{"value": "0"},
{"value": "2"},
{"value": "0"},
{"value": "47"}
],
[
{"value": "1fd775"},
{"value": "5264ac0"},
{"value": "1fff"},
{"value": "55a38d"},
{"value": "e"},
{"value": "4dd37fc"},
{"value": "1d5"},
{"value": "1fdfd"},
{"value": "e05"},
{"value": "b5db63fc"},
{"value": "28e9d0ae"},
{"value": "c74ce"},
{"value": "3e6e"},
{"value": "0"},
{"value": "d8"},
{"value": "a019"},
{"value": "80"},
{"value": "d44c482"},
{"value": "8b5a"},
{"value": "ee25bee"},
{"value": "0"},
{"value": "2d126"},
{"value": "7d5"},
{"value": "2"},
{"value": "5e"},
{"value": "398eccd4"},
{"value": "0"},
{"value": "6b"},
{"value": "0"},
{"value": "b"}
],
[
{"value": "cd92e9"},
{"value": "c3e6ba"},
{"value": "1fff"},
{"value": "7be46f"},
{"value": "5"},
{"value": "c1f87b"},
{"value": "85"},
{"value": "1280c"},
{"value": "19a"},
{"value": "2895f7b2"},
{"value": "30e3a12d"},
{"value": "46cc9"},
{"value": "26a8"},
{"value": "0"},
{"value": "9a"},
{"value": "2900a"},
{"value": "0"},
{"value": "136a31c2"},
{"value": "10823"},
{"value": "151f81c6"},
{"value": "0"},
{"value": "16fc2"},
{"value": "59"},
{"value": "b"},
{"value": "69"},
{"value": "2fabbfc2"},
{"value": "0"},
{"value": "60"},
{"value": "0"},
{"value": "65"}
],
[
{"value": "196a034b"},
{"value": "36dbdfe"},
{"value": "1fff"},
{"value": "e321fd"},
{"value": "4"},
{"value": "5d836aa"},
{"value": "14a"},
{"value": "16e74"},
{"value": "919"},
{"value": "141273c2"},
{"value": "79eb672c"},
{"value": "ad7a0"},
{"value": "2590"},
{"value": "0"},
{"value": "87"},
{"value": "1c073"},
{"value": "80"},
{"value": "1c1fe45c"},
{"value": "3adca"},
{"value": "ee1d354"},
{"value": "0"},
{"value": "edd1"},
{"value": "3aa"},
{"value": "c"},
{"value": "10"},
{"value": "23743dfb"},
{"value": "0"},
{"value": "1b"},
{"value": "0"},
{"value": "41"}
],
[
{"value": "14bdba38"},
{"value": "55a2d5f"},
{"value": "1fff"},
{"value": "d76077"},
{"value": "3"},
{"value": "55251ec"},
{"value": "2d4"},
{"value": "147f7"},
{"value": "f58"},
{"value": "f082fb9a"},
{"value": "6910dd3a"},
{"value": "f25e0"},
{"value": "2718"},
{"value": "0"},
{"value": "19"},
{"value": "14917"},
{"value": "0"},
{"value": "1dd97809"},
{"value": "1f55c"},
{"value": "61f1254"},
{"value": "0"},
{"value": "37076"},
{"value": "21b"},
{"value": "f"},
{"value": "15"},
{"value": "24d19e6b"},
{"value": "0"},
{"value": "4"},
{"value": "0"},
{"value": "5c"}
],
[
{"value": "19908aa8"},
{"value": "1d9fac1"},
{"value": "1fff"},
{"value": "f5d538"},
{"value": "6"},
{"value": "2e0711f"},
{"value": "396"},
{"value": "10fbe"},
{"value": "ac4"},
{"value": "83b04aa9"},
{"value": "2506065"},
{"value": "1a4bde"},
{"value": "9f8"},
{"value": "0"},
{"value": "2f"},
{"value": "1f189"},
{"value": "80"},
{"value": "ccfa4f0"},
{"value": "130b2"},
{"value": "164e6f97"},
{"value": "0"},
{"value": "20624"},
{"value": "69d"},
{"value": "d"},
{"value": "40"},
{"value": "2dc59f0"},
{"value": "0"},
{"value": "31"},
{"value": "0"},
{"value": "3d"}
],
[
{"value": "2728d76"},
{"value": "29d583c"},
{"value": "1fff"},
{"value": "372f88"},
{"value": "9"},
{"value": "7be465b"},
{"value": "1aa"},
{"value": "1b586"},
{"value": "cc8"},
{"value": "4fee1a24"},
{"value": "e294290c"},
{"value": "10b678"},
{"value": "236c"},
{"value": "0"},
{"value": "78"},
{"value": "b2c5"},
{"value": "0"},
{"value": "108d72ec"},
{"value": "5f30"},
{"value": "e4f39ba"},
{"value": "0"},
{"value": "34cbb"},
{"value": "4a1"},
{"value": "f"},
{"value": "56"},
{"value": "e46438d"},
{"value": "0"},
{"value": "57"},
{"value": "0"},
{"value": "67"}
],
[
{"value": "17f45370"},
{"value": "5986268"},
{"value": "1fff"},
{"value": "cef9fe"},
{"value": "f"},
{"value": "533c929"},
{"value": "232"},
{"value": "22b5"},
{"value": "259"},
{"value": "5532e43e"},
{"value": "9c032c0f"},
{"value": "12a2a7"},
{"value": "3ee2"},
{"value": "0"},
{"value": "54"},
{"value": "364d8"},
{"value": "0"},
{"value": "1aa3799"},
{"value": "39287"},
{"value": "1b50ecfe"},
{"value": "0"},
{"value": "38d8b"},
{"value": "78c"},
{"value": "5"},
{"value": "10"},
{"value": "39aba041"},
{"value": "0"},
{"value": "62"},
{"value": "0"},
{"value": "7a"}
],
[
{"value": "12cdc828"},
{"value": "5de2776"},
{"value": "1fff"},
{"value": "6a5e5b"},
{"value": "f"},
{"value": "452e123"},
{"value": "391"},
{"value": "1f915"},
{"value": "6eb"},
{"value": "f0e5b02c"},
{"value": "365241a3"},
{"value": "e516"},
{"value": "258d"},
{"value": "0"},
{"value": "f5"},
{"value": "253ff"},
{"value": "0"},
{"value": "2ae8e13"},
{"value": "25c8b"},
{"value": "6544b5c"},
{"value": "0"},
{"value": "35aac"},
{"value": "46c"},
{"value": "4"},
{"value": "66"},
{"value": "14895d0d"},
{"value": "0"},
{"value": "6f"},
{"value": "0"},
{"value": "25"}
]
]}
